setup.py
bucket_observer/__init__.py
bucket_observer/observers.py
bucket_observer.egg-info/PKG-INFO
bucket_observer.egg-info/SOURCES.txt
bucket_observer.egg-info/dependency_links.txt
bucket_observer.egg-info/requires.txt
bucket_observer.egg-info/top_level.txt