Metadata-Version: 1.0
Name: bucket-observer
Version: 0.1
Summary: Pulls S3 buckets, observes changes and emits blinker signals.
Home-page: https://bitbucket.org/fabian/bucket_observer
Author: Fabian Topfstedt
Author-email: topfstedt@schneevonmorgen.com
License: UNKNOWN
Keywords: s3,bucket,observer
Platform: UNKNOWN
